whatsapp_messager/__init__.py
whatsapp_messager/messaging.py
whatsapp_messager-0.0.4.dist-info/METADATA
whatsapp_messager-0.0.4.dist-info/WHEEL
whatsapp_messager-0.0.4.dist-info/top_level.txt
whatsapp_messager-0.0.4.dist-info/RECORD
