Metadata-Version: 2.1
Name: whatsapp_messager
Version: 0.0.4
Summary: WhatsApp message sender using WhatsApp Business API
Home-page: https://github.com/John-sys/whatsapp-sender_library
Author: John Gbaya-kokoya
Author-email: John Gbaya-Kokoya <gbayakokoyajohnjr@gmail.com>
Project-URL: Homepage, https://github.com/John-sys/whatsapp-sender_library?tab=readme-ov-file
Project-URL: Documentation, https://github.com/John-sys/whatsapp-sender_library?tab=readme-ov-file
Project-URL: Repository, https://github.com/John-sys/whatsapp-sender_library
Project-URL: Issues, https://github.com/John-sys/whatsapp-sender_library/issues
Keywords: whatsapp,messaging,automation,api
Classifier: Development Status :: 3 - Alpha
Classifier: Intended Audience :: Developers
Classifier: License :: OSI Approved :: MIT License
Classifier: Programming Language :: Python :: 3
Classifier: Programming Language :: Python :: 3.7
Classifier: Programming Language :: Python :: 3.8
Classifier: Programming Language :: Python :: 3.9
Classifier: Programming Language :: Python :: 3.10
Classifier: Operating System :: OS Independent
Requires-Python: >=3.7
Requires-Dist: requests>=2.25.0
Requires-Dist: setuptools>=42.0.0
